proventra_core/__init__.py
proventra_core/analyzers/__init__.py
proventra_core/analyzers/base.py
proventra_core/analyzers/results.py
proventra_core/analyzers/transformers.py
proventra_core/providers/__init__.py
proventra_core/providers/llm.py
proventra_core/sanitizers/__init__.py
proventra_core/sanitizers/base.py
proventra_core/sanitizers/llm.py
proventra_core/sanitizers/results.py
proventra_core/services/__init__.py
proventra_core/services/guard.py
proventra_core-0.1.3.dist-info/licenses/LICENSE
proventra_core-0.1.3.dist-info/METADATA
proventra_core-0.1.3.dist-info/WHEEL
proventra_core-0.1.3.dist-info/top_level.txt
proventra_core-0.1.3.dist-info/RECORD
