Metadata-Version: 2.4
Name: proventra-core
Version: 0.1.3
Summary: Prompt injection detection and prevention library for LLM applications
Author: Gasper Pregelj
License: MIT
Project-URL: Repository, https://github.com/proventra/proventra-core
Classifier: Intended Audience :: Developers
Classifier: License :: OSI Approved :: MIT License
Classifier: Programming Language :: Python :: 3
Classifier: Programming Language :: Python :: 3.11
Classifier: Topic :: Software Development :: Libraries :: Python Modules
Requires-Python: <4.0,>=3.11
License-File: LICENSE
Requires-Dist: torch>=2.6.0
Requires-Dist: transformers>=4.51.1
Requires-Dist: numpy>=2.2.4
Requires-Dist: langchain>=0.3.23
Requires-Dist: langchain-core>=0.3.51
Requires-Dist: python-dotenv>=1.1.0
Requires-Dist: tiktoken>=0.9.0
Provides-Extra: google
Requires-Dist: langchain-google-genai>=2.1.2; extra == "google"
Provides-Extra: anthropic
Requires-Dist: langchain-anthropic>=0.3.10; extra == "anthropic"
Provides-Extra: openai
Requires-Dist: langchain-openai>=0.3.12; extra == "openai"
Provides-Extra: mistral
Requires-Dist: langchain-mistralai>=0.2.10; extra == "mistral"
Provides-Extra: all
Requires-Dist: langchain-google-genai>=2.1.2; extra == "all"
Requires-Dist: langchain-anthropic>=0.3.10; extra == "all"
Requires-Dist: langchain-openai>=0.3.12; extra == "all"
Requires-Dist: langchain-mistralai>=0.2.10; extra == "all"
Provides-Extra: api
Requires-Dist: fastapi>=0.115.12; extra == "api"
Requires-Dist: uvicorn>=0.34.0; extra == "api"
Provides-Extra: runpod
Requires-Dist: runpod>=1.7.9; extra == "runpod"
Provides-Extra: dev
Requires-Dist: pytest>=8.3.5; extra == "dev"
Requires-Dist: isort>=6.0.1; extra == "dev"
Requires-Dist: mypy>=1.15.0; extra == "dev"
Requires-Dist: ruff>=0.11.4; extra == "dev"
Requires-Dist: build>=1.2.2.post1; extra == "dev"
Requires-Dist: matplotlib>=3.10.1; extra == "dev"
Requires-Dist: pandas>=2.2.3; extra == "dev"
Requires-Dist: scikit-learn>=1.6.1; extra == "dev"
Dynamic: license-file
